transformers/__init__.py
transformers/exceptions.py
transformers/factories.py
transformers/transformers.py
transformers/impl/__init__.py
transformers/impl/factories_impl.py
transformers/impl/transformers_impl.py
jsonapi_transformer-1.0.0.dist-info/LICENSE.txt
jsonapi_transformer-1.0.0.dist-info/METADATA
jsonapi_transformer-1.0.0.dist-info/WHEEL
jsonapi_transformer-1.0.0.dist-info/top_level.txt
jsonapi_transformer-1.0.0.dist-info/RECORD
