Metadata-Version: 2.1
Name: jsonapi-transformer
Version: 1.0.0
Summary: A Python library for producing, consuming, and manipulating JSON:API data.
Home-page: https://github.com/boost-insurance/jsonapi-transformer
Author: Boost Digital Insurance
Author-email: techopensource@boostdigitalinsurance.io
Project-URL: Bug Tracker, https://github.com/boost-insurance/jsonapi-transformer/issues
Classifier: Development Status :: 5 - Production/Stable
Classifier: Intended Audience :: Developers
Classifier: License :: OSI Approved :: MIT License
Classifier: Operating System :: OS Independent
Classifier: Programming Language :: Python :: 3
Classifier: Programming Language :: Python :: 3.7
Classifier: Programming Language :: Python :: 3.8
Classifier: Programming Language :: Python :: 3.9
Classifier: Programming Language :: Python :: 3.10
Classifier: Topic :: Software Development :: Libraries
Classifier: Typing :: Typed
Requires-Python: >=3.7
License-File: LICENSE.txt
Provides-Extra: dev
Requires-Dist: pytest ; extra == 'dev'
Requires-Dist: pytest-cov ; extra == 'dev'
Requires-Dist: pytest-clarity ; extra == 'dev'
Requires-Dist: black (==22.3.0) ; extra == 'dev'
Requires-Dist: flake8-bugbear ; extra == 'dev'
Requires-Dist: flake8 ; extra == 'dev'
Requires-Dist: isort ; extra == 'dev'
Requires-Dist: mypy ; extra == 'dev'
Requires-Dist: pre-commit ; extra == 'dev'
Requires-Dist: rich ; extra == 'dev'
Provides-Extra: tests
Requires-Dist: pytest ; extra == 'tests'
Requires-Dist: pytest-cov ; extra == 'tests'
Requires-Dist: pytest-clarity ; extra == 'tests'
Requires-Dist: black (==22.3.0) ; extra == 'tests'
Requires-Dist: flake8-bugbear ; extra == 'tests'
Requires-Dist: flake8 ; extra == 'tests'
Requires-Dist: isort ; extra == 'tests'
Requires-Dist: mypy ; extra == 'tests'
